llm_apple.py
llm_apple-0.2.0.dist-info/licenses/LICENSE
llm_apple-0.2.0.dist-info/METADATA
llm_apple-0.2.0.dist-info/WHEEL
llm_apple-0.2.0.dist-info/entry_points.txt
llm_apple-0.2.0.dist-info/top_level.txt
llm_apple-0.2.0.dist-info/RECORD
