Metadata-Version: 2.4
Name: llm-apple
Version: 0.2.0
Summary: LLM plugin for Apple Foundation Models (Apple Intelligence)
Author: Ben Tucker
License-Expression: MIT
Project-URL: Homepage, https://github.com/btucker/llm-apple
Project-URL: Issues, https://github.com/btucker/llm-apple/issues
Project-URL: Changelog, https://github.com/btucker/llm-apple/releases
Requires-Python: >=3.9
License-File: LICENSE
Requires-Dist: llm>=0.15
Requires-Dist: apple-foundation-models>=0.2.0
Provides-Extra: test
Requires-Dist: pytest>=7.0; extra == "test"
Requires-Dist: pytest-asyncio>=0.21.0; extra == "test"
Requires-Dist: pytest-cov>=4.0; extra == "test"
Provides-Extra: dev
Requires-Dist: pre-commit>=3.0; extra == "dev"
Requires-Dist: black>=23.0; extra == "dev"
Dynamic: license-file
